pyclspv.cpython-311-x86_64-linux-gnu.so
pyclspv-0.0.1.dist-info/METADATA
pyclspv-0.0.1.dist-info/WHEEL
pyclspv-0.0.1.dist-info/RECORD
pyclspv-0.0.1.dist-info/licenses/LICENSE
