Metadata-Version: 2.4
Name: pyclspv
Version: 0.0.1
Summary: Python bindings for clspv, a OpenCL C to SPIR-V compiler
Author-Email: cookie <softcookiepp@mailfence.com>
License-File: LICENSE
Classifier: Programming Language :: Python :: 3.9
Requires-Python: >=3.9
Provides-Extra: test
Requires-Dist: pytest; extra == "test"
